ingot_prometheus/__init__.py
ingot_prometheus/bootstrap/__init__.py
ingot_prometheus/bootstrap/scaffolding/__init__.py
ingot_prometheus/scripts/__init__.py
ingot_prometheus/scripts/ingot_prometheus.py
ingot_prometheus/tests/__init__.py
ingot_prometheus/tests/functionals/__init__.py
ingot_prometheus/tests/units/__init__.py
ingot_prometheus/tests/units/scripts/__init__.py
ingot_prometheus/tests/units/scripts/test_ingot_prometheus.py
scripts/__init__.py
scripts/create_package_version_file.py
ingot_prometheus-0.1.0.dist-info/LICENSE
ingot_prometheus-0.1.0.dist-info/METADATA
ingot_prometheus-0.1.0.dist-info/WHEEL
ingot_prometheus-0.1.0.dist-info/entry_points.txt
ingot_prometheus-0.1.0.dist-info/top_level.txt
ingot_prometheus-0.1.0.dist-info/RECORD
